surfingcrypto/__init__.py
surfingcrypto/config.py
surfingcrypto/scraper.py
surfingcrypto/ts.py
surfingcrypto/algotrading/__init__.py
surfingcrypto/algotrading/backtesting.py
surfingcrypto/algotrading/features.py
surfingcrypto/algotrading/model.py
surfingcrypto/algotrading/signals.py
surfingcrypto/extra/__init__.py
surfingcrypto/extra/gtrends.py
surfingcrypto/portfolio/__init__.py
surfingcrypto/portfolio/coinbase.py
surfingcrypto/portfolio/portfolio.py
surfingcrypto/portfolio/tracker.py
surfingcrypto/reporting/__init__.py
surfingcrypto/reporting/figures.py
surfingcrypto/reporting/plotting.py
surfingcrypto/reporting/reporting.py
surfingcrypto-0.6.2.dist-info/METADATA
surfingcrypto-0.6.2.dist-info/WHEEL
surfingcrypto-0.6.2.dist-info/top_level.txt
surfingcrypto-0.6.2.dist-info/RECORD
