Metadata-Version: 2.1
Name: surfingcrypto
Version: 0.6.2
Summary: Customizable interface to cryptocurrencies.
Home-page: https://github.com/giocaizzi/surfingcrypto
Author: giocaizzi
Author-email: giocaizzi@gmail.com
Project-URL: Documentation, https://giocaizzi.github.io/surfingcrypto/
Project-URL: Bug Reports, https://github.com/giocaizzi/surfingcrypto/issues
Project-URL: Source, https://github.com/giocaizzi/surfingcrypto
Classifier: Programming Language :: Python :: 3.7
Classifier: Programming Language :: Python :: 3.8
Classifier: Programming Language :: Python :: 3.9
Requires-Dist: matplotlib
Requires-Dist: mplfinance
Requires-Dist: numpy
Requires-Dist: pandas
Requires-Dist: coinbase
Requires-Dist: pandas-ta
Requires-Dist: python-dateutil
Requires-Dist: pytrends
Requires-Dist: cryptocmd
Requires-Dist: calplot
Requires-Dist: scikit-learn
Provides-Extra: dev
